MANIFEST.in
README.rst
setup.cfg
setup.py
eacheck/__init__.py
eacheck/console_script.py
eacheck/style_errors.py
eacheck/validator.py
eacheck.egg-info/PKG-INFO
eacheck.egg-info/SOURCES.txt
eacheck.egg-info/dependency_links.txt
eacheck.egg-info/entry_points.txt
eacheck.egg-info/requires.txt
eacheck.egg-info/top_level.txt
eacheck/schema/article/1.0.0/eruditarticle.xsd
eacheck/schema/article/1.0.2persee/eruditarticle.xsd
eacheck/schema/article/2.0.0/eruditarticle.xsd
eacheck/schema/article/2.0.0/eruditarticle_old.xsd
eacheck/schema/article/2.0.1erudit/eruditarticle.xsd
eacheck/schema/article/3.0.0/eruditarticle.xsd
eacheck/schema/article/3.0.0/old_eruditarticle.xsd
eacheck/schema/article/3.0.0/en/eruditarticle.xsd
eacheck/schema/articleprod/0.1.0/eruditarticleprod.xsd
eacheck/schema/chapitre/1.2.0/eruditchapitre.xsd
eacheck/schema/chapitre/1.3.0/eruditchapitre.xsd
eacheck/schema/corpus/0.10.0/eruditcorpus.xsd
eacheck/schema/corpus/1.0.0/eruditcorpus.xsd
eacheck/schema/dc/0.1.0/eruditdc.xsd
eacheck/schema/dc/0.1.0/eruditdcterms.xsd
eacheck/schema/dc/0.2.0/eruditdc.xsd
eacheck/schema/dc/0.2.0/eruditdcmitype.xsd
eacheck/schema/dc/0.2.0/eruditdcterms.xsd
eacheck/schema/dc/0.3.0/eruditdcterms.xsd
eacheck/schema/doc/0.1.0/eruditdoc.xsd
eacheck/schema/docunit/0.2.2/eruditdocunit.xsd
eacheck/schema/docunit/1.0.0/eruditdocunit.xsd
eacheck/schema/etdms/1.0/eruditetdms.xsd
eacheck/schema/exodic/1.1/exodic.1.1.xsd
eacheck/schema/exodic/1.2/exodic.1.2.xsd
eacheck/schema/id/1.0.0/eruditid.xsd
eacheck/schema/id/1.0.1/eruditid.xsd
eacheck/schema/id/1.1.0/eruditid.xsd
eacheck/schema/id/1.2.0/eruditid.xsd
eacheck/schema/id/1.3.0/eruditid.xsd
eacheck/schema/lang/0.1.0/eruditlang.xsd
eacheck/schema/lang/1.0.0/eruditlang.xsd
eacheck/schema/lang/1.1.0/eruditlang.xsd
eacheck/schema/lang/1.2.0/eruditlang.xsd
eacheck/schema/lang/1.3.0/eruditlang.xsd
eacheck/schema/lang/1.4.0/eruditlang.xsd
eacheck/schema/lang/1.5.0/eruditlang.xsd
eacheck/schema/lot/1.0.0/eruditlot.xsd
eacheck/schema/lot/1.0.1/eruditlot.xsd
eacheck/schema/marc/1.0.0/eruditmarc.xsd
eacheck/schema/marc/1.1.0/eruditmarc.xsd
eacheck/schema/marc/1.2.0/eruditmarc.xsd
eacheck/schema/mathml/2.0/mathml2.xsd
